ows_lib/__init__.py
ows_lib/client/__init__.py
ows_lib/client/enums.py
ows_lib/client/exceptions.py
ows_lib/client/maps.py
ows_lib/client/mixins.py
ows_lib/client/utils.py
ows_lib/client/csw/__init__.py
ows_lib/client/csw/csw202.py
ows_lib/client/csw/mixins.py
ows_lib/client/wfs/__init__.py
ows_lib/client/wfs/mixins.py
ows_lib/client/wfs/wfs200.py
ows_lib/client/wms/__init__.py
ows_lib/client/wms/mixins.py
ows_lib/client/wms/wms111.py
ows_lib/client/wms/wms130.py
ows_lib/contrib/fes/parser.py
ows_lib/contrib/fes/v11/parser.py
ows_lib/models/ogc_request.py
ows_lib/xml_mapper/__init__.py
ows_lib/xml_mapper/consts.py
ows_lib/xml_mapper/exceptions.py
ows_lib/xml_mapper/mixins.py
ows_lib/xml_mapper/namespaces.py
ows_lib/xml_mapper/utils.py
ows_lib/xml_mapper/capabilities/__init__.py
ows_lib/xml_mapper/capabilities/mixins.py
ows_lib/xml_mapper/capabilities/csw/csw202.py
ows_lib/xml_mapper/capabilities/wfs/__init__.py
ows_lib/xml_mapper/capabilities/wfs/mixins.py
ows_lib/xml_mapper/capabilities/wfs/wfs200.py
ows_lib/xml_mapper/capabilities/wms/__init__.py
ows_lib/xml_mapper/capabilities/wms/mixins.py
ows_lib/xml_mapper/capabilities/wms/wms111.py
ows_lib/xml_mapper/capabilities/wms/wms130.py
ows_lib/xml_mapper/gml/__init__.py
ows_lib/xml_mapper/gml/gml.py
ows_lib/xml_mapper/iso_metadata/__init__.py
ows_lib/xml_mapper/iso_metadata/iso_metadata.py
ows_lib/xml_mapper/xml_requests/__init__.py
ows_lib/xml_mapper/xml_requests/utils.py
ows_lib/xml_mapper/xml_requests/csw/get_records.py
ows_lib/xml_mapper/xml_requests/csw/get_records_by_id.py
ows_lib/xml_mapper/xml_requests/csw/query.py
ows_lib/xml_mapper/xml_requests/wfs/__init__.py
ows_lib/xml_mapper/xml_requests/wfs/get_feature.py
ows_lib/xml_mapper/xml_responses/__init__.py
ows_lib/xml_mapper/xml_responses/consts.py
ows_lib/xml_mapper/xml_responses/csw/__init__.py
ows_lib/xml_mapper/xml_responses/csw/achnowledgment.py
ows_lib/xml_mapper/xml_responses/csw/get_record_by_id.py
ows_lib/xml_mapper/xml_responses/csw/get_records.py
django_ows_lib-0.17.1.dist-info/LICENSE
django_ows_lib-0.17.1.dist-info/METADATA
django_ows_lib-0.17.1.dist-info/WHEEL
django_ows_lib-0.17.1.dist-info/top_level.txt
django_ows_lib-0.17.1.dist-info/RECORD
