Metadata-Version: 2.1
Name: django-ows-lib
Version: 0.17.1
Summary: Well layered ows lib with a client implementation to communicate with ogc services with django based objects, including xml mapper classes to serialize and deserialize ows xml files, such as capabilities.
Home-page: https://github.com/mrmap-community/django-ows-lib
Author: mrmap-community
Author-email: jonas.kiefer@live.com
License: MIT
Classifier: Development Status :: 3 - Alpha
Classifier: Intended Audience :: Developers
Classifier: Natural Language :: English
Classifier: Programming Language :: Python :: 3.9
Classifier: Programming Language :: Python :: 3.10
Classifier: Programming Language :: Python :: 3.11
Classifier: Programming Language :: Python :: 3.12
Classifier: Topic :: Internet :: WWW/HTTP
Classifier: Environment :: Web Environment
Classifier: Framework :: Django
Classifier: Topic :: Software Development :: Libraries
Classifier: License :: OSI Approved :: MIT License
Classifier: Operating System :: OS Independent
Requires-Python: >=3.8
License-File: LICENSE
Requires-Dist: camel-converter >=3.0.0
Requires-Dist: django-epsg-cache >=0.2.0
Requires-Dist: django >=3.0
Requires-Dist: eulxml >=1.1.3
Requires-Dist: isodate >=0.6.1
Requires-Dist: pygeofilter >=0.2.1
Requires-Dist: pygml >=0.2.2
Requires-Dist: requests >=2.23.0
